bensix_theory/__init__.py
bensix_theory/main.py
bensix_theory_sangeda-0.1.1.dist-info/licenses/LICENSE
bensix_theory_sangeda-0.1.1.dist-info/METADATA
bensix_theory_sangeda-0.1.1.dist-info/WHEEL
bensix_theory_sangeda-0.1.1.dist-info/top_level.txt
bensix_theory_sangeda-0.1.1.dist-info/RECORD
